{
  "updated_at": "2026-07-22T15:40:38.836290+00:00",
  "instruments": {
    "XAU/USD": {
      "interval": "5min",
      "meta": {
        "symbol": "XAU/USD",
        "interval": "5min",
        "currency_base": "Gold Spot",
        "currency_quote": "US Dollar",
        "type": "Precious Metal"
      },
      "latest_close": 4157.17923,
      "latest_datetime": "2026-07-23 01:35:00",
      "signal": "SELL",
      "regime": "trending",
      "trade_setup": {
        "entry": 4157.17923,
        "stop_loss": 4163.496409626869,
        "take_profit": 4144.544870746263,
        "risk_reward": 2.0
      },
      "indicators": {
        "rsi": 62.11741730250601,
        "rsi_ma": 61.99304834797341,
        "macd": 5.525912227560939,
        "macd_signal": 5.911619085266841,
        "macd_histogram": -0.3857068577059022,
        "alma": 4157.790759718343,
        "adx": 29.85569849468078,
        "atr": 4.211453084578914
      },
      "candles": [
        {
          "datetime": "2026-07-22 21:30:00",
          "close": 4120.39398,
          "rsi": null,
          "rsi_ma": null,
          "macd": null,
          "macd_signal": null,
          "alma": null,
          "adx": null
        },
        {
          "datetime": "2026-07-22 21:35:00",
          "close": 4118.17192,
          "rsi": null,
          "rsi_ma": null,
          "macd": null,
          "macd_signal": null,
          "alma": null,
          "adx": null
        },
        {
          "datetime": "2026-07-22 21:40:00",
          "close": 4114.35235,
          "rsi": null,
          "rsi_ma": null,
          "macd": null,
          "macd_signal": null,
          "alma": null,
          "adx": null
        },
        {
          "datetime": "2026-07-22 21:45:00",
          "close": 4119.52919,
          "rsi": null,
          "rsi_ma": null,
          "macd": null,
          "macd_signal": null,
          "alma": null,
          "adx": null
        },
        {
          "datetime": "2026-07-22 21:50:00",
          "close": 4118.33622,
          "rsi": null,
          "rsi_ma": null,
          "macd": null,
          "macd_signal": null,
          "alma": null,
          "adx": null
        },
        {
          "datetime": "2026-07-22 21:55:00",
          "close": 4122.81229,
          "rsi": null,
          "rsi_ma": null,
          "macd": null,
          "macd_signal": null,
          "alma": null,
          "adx": null
        },
        {
          "datetime": "2026-07-22 22:00:00",
          "close": 4125.83908,
          "rsi": null,
          "rsi_ma": null,
          "macd": null,
          "macd_signal": null,
          "alma": null,
          "adx": null
        },
        {
          "datetime": "2026-07-22 22:05:00",
          "close": 4123.93771,
          "rsi": null,
          "rsi_ma": null,
          "macd": null,
          "macd_signal": null,
          "alma": null,
          "adx": null
        },
        {
          "datetime": "2026-07-22 22:10:00",
          "close": 4126.27241,
          "rsi": null,
          "rsi_ma": null,
          "macd": null,
          "macd_signal": null,
          "alma": 4124.416538746944,
          "adx": null
        },
        {
          "datetime": "2026-07-22 22:15:00",
          "close": 4127.42721,
          "rsi": null,
          "rsi_ma": null,
          "macd": null,
          "macd_signal": null,
          "alma": 4125.552377156217,
          "adx": null
        },
        {
          "datetime": "2026-07-22 22:20:00",
          "close": 4128.06826,
          "rsi": null,
          "rsi_ma": null,
          "macd": null,
          "macd_signal": null,
          "alma": 4126.589654097667,
          "adx": null
        },
        {
          "datetime": "2026-07-22 22:25:00",
          "close": 4132.80593,
          "rsi": null,
          "rsi_ma": null,
          "macd": null,
          "macd_signal": null,
          "alma": 4128.420273133951,
          "adx": null
        },
        {
          "datetime": "2026-07-22 22:30:00",
          "close": 4129.1173,
          "rsi": null,
          "rsi_ma": null,
          "macd": null,
          "macd_signal": null,
          "alma": 4129.479317903892,
          "adx": null
        },
        {
          "datetime": "2026-07-22 22:35:00",
          "close": 4125.07511,
          "rsi": null,
          "rsi_ma": null,
          "macd": null,
          "macd_signal": null,
          "alma": 4128.907745827585,
          "adx": null
        },
        {
          "datetime": "2026-07-22 22:40:00",
          "close": 4127.77174,
          "rsi": 58.97290139411656,
          "rsi_ma": null,
          "macd": null,
          "macd_signal": null,
          "alma": 4128.066744808146,
          "adx": null
        },
        {
          "datetime": "2026-07-22 22:45:00",
          "close": 4120.71396,
          "rsi": 49.77117955108037,
          "rsi_ma": null,
          "macd": null,
          "macd_signal": null,
          "alma": 4125.974734565814,
          "adx": null
        },
        {
          "datetime": "2026-07-22 22:50:00",
          "close": 4118.76666,
          "rsi": 47.5659091987198,
          "rsi_ma": null,
          "macd": null,
          "macd_signal": null,
          "alma": 4123.39767364042,
          "adx": null
        },
        {
          "datetime": "2026-07-22 22:55:00",
          "close": 4114.72956,
          "rsi": 43.284043361424615,
          "rsi_ma": null,
          "macd": null,
          "macd_signal": null,
          "alma": 4120.2098587103665,
          "adx": null
        },
        {
          "datetime": "2026-07-22 23:00:00",
          "close": 4118.6962,
          "rsi": 48.216534644559175,
          "rsi_ma": null,
          "macd": null,
          "macd_signal": null,
          "alma": 4118.401522022222,
          "adx": null
        },
        {
          "datetime": "2026-07-22 23:05:00",
          "close": 4119.91584,
          "rsi": 49.666026684726404,
          "rsi_ma": null,
          "macd": null,
          "macd_signal": null,
          "alma": 4118.162955336232,
          "adx": null
        },
        {
          "datetime": "2026-07-22 23:10:00",
          "close": 4124.17448,
          "rsi": 54.45946163495567,
          "rsi_ma": null,
          "macd": null,
          "macd_signal": null,
          "alma": 4119.7309961264355,
          "adx": null
        },
        {
          "datetime": "2026-07-22 23:15:00",
          "close": 4128.07652,
          "rsi": 58.371325047658225,
          "rsi_ma": null,
          "macd": null,
          "macd_signal": null,
          "alma": 4122.529357507846,
          "adx": null
        },
        {
          "datetime": "2026-07-22 23:20:00",
          "close": 4132.5409,
          "rsi": 62.355523017768284,
          "rsi_ma": null,
          "macd": null,
          "macd_signal": null,
          "alma": 4126.146405976997,
          "adx": null
        },
        {
          "datetime": "2026-07-22 23:25:00",
          "close": 4133.92523,
          "rsi": 63.52139197930768,
          "rsi_ma": null,
          "macd": null,
          "macd_signal": null,
          "alma": 4129.557919921942,
          "adx": null
        },
        {
          "datetime": "2026-07-22 23:30:00",
          "close": 4143.19658,
          "rsi": 70.18201424414808,
          "rsi_ma": null,
          "macd": null,
          "macd_signal": null,
          "alma": 4134.018937540228,
          "adx": null
        },
        {
          "datetime": "2026-07-22 23:35:00",
          "close": 4140.7946,
          "rsi": 66.78001544388732,
          "rsi_ma": null,
          "macd": 5.086568364600361,
          "macd_signal": null,
          "alma": 4137.566368484953,
          "adx": null
        },
        {
          "datetime": "2026-07-22 23:40:00",
          "close": 4142.53054,
          "rsi": 67.98775815124708,
          "rsi_ma": null,
          "macd": 5.685772473311855,
          "macd_signal": null,
          "alma": 4140.165861141113,
          "adx": null
        },
        {
          "datetime": "2026-07-22 23:45:00",
          "close": 4146.33149,
          "rsi": 70.51538300938552,
          "rsi_ma": 57.974961954498916,
          "macd": 6.393648940555198,
          "macd_signal": null,
          "alma": 4142.400055402112,
          "adx": null
        },
        {
          "datetime": "2026-07-22 23:50:00",
          "close": 4146.08236,
          "rsi": 70.12455542874446,
          "rsi_ma": 58.77150867125805,
          "macd": 6.855517295910464,
          "macd_signal": null,
          "alma": 4144.109955033813,
          "adx": 22.873500282462437
        },
        {
          "datetime": "2026-07-22 23:55:00",
          "close": 4148.82111,
          "rsi": 71.96416585804796,
          "rsi_ma": 60.35672197889859,
          "macd": 7.357730197731138,
          "macd_signal": null,
          "alma": 4145.885735819673,
          "adx": 24.412327962511338
        },
        {
          "datetime": "2026-07-23 00:00:00",
          "close": 4160.17586,
          "rsi": 78.00989470251112,
          "rsi_ma": 62.53129237202654,
          "macd": 8.573145090066639,
          "macd_signal": null,
          "alma": 4149.789406529282,
          "adx": 26.01790934280951
        },
        {
          "datetime": "2026-07-23 00:05:00",
          "close": 4154.69507,
          "rsi": 70.14680310700702,
          "rsi_ma": 64.45006092528243,
          "macd": 8.990479548847254,
          "macd_signal": null,
          "alma": 4152.9031965329505,
          "adx": 28.51633732396071
        },
        {
          "datetime": "2026-07-23 00:10:00",
          "close": 4157.56746,
          "rsi": 71.7537074453421,
          "rsi_ma": 66.13128755390979,
          "macd": 9.444131907734093,
          "macd_signal": null,
          "alma": 4155.318581578227,
          "adx": 30.935979718627628
        },
        {
          "datetime": "2026-07-23 00:15:00",
          "close": 4151.87919,
          "rsi": 64.3649700845139,
          "rsi_ma": 67.18121208246603,
          "macd": 9.238166981987495,
          "macd_signal": 7.513906755638278,
          "alma": 4155.313233542819,
          "adx": 33.18279051367548
        },
        {
          "datetime": "2026-07-23 00:20:00",
          "close": 4150.23866,
          "rsi": 62.37020520023411,
          "rsi_ma": 67.74626519427163,
          "macd": 8.840651704186172,
          "macd_signal": 7.779255745347856,
          "alma": 4153.823839261681,
          "adx": 34.12216325379087
        },
        {
          "datetime": "2026-07-23 00:25:00",
          "close": 4146.22388,
          "rsi": 57.66060946198137,
          "rsi_ma": 67.69549979529471,
          "macd": 8.108192592470763,
          "macd_signal": 7.845043114772437,
          "alma": 4151.224209041952,
          "adx": 34.62473830901253
        },
        {
          "datetime": "2026-07-23 00:30:00",
          "close": 4150.32939,
          "rsi": 60.91110722458391,
          "rsi_ma": 67.59232723863869,
          "macd": 7.769432632095776,
          "macd_signal": 7.829921018237105,
          "alma": 4149.7550376337,
          "adx": 34.08269746841175
        },
        {
          "datetime": "2026-07-23 00:35:00",
          "close": 4150.66088,
          "rsi": 61.17032040277834,
          "rsi_ma": 67.42439355460088,
          "macd": 7.441925510638498,
          "macd_signal": 7.752321916717384,
          "alma": 4149.488598100298,
          "adx": 33.62331615503727
        },
        {
          "datetime": "2026-07-23 00:40:00",
          "close": 4151.2263,
          "rsi": 61.6376192158042,
          "rsi_ma": 66.81407962400489,
          "macd": 7.1456280734780835,
          "macd_signal": 7.630983148069523,
          "alma": 4150.0483209141275,
          "adx": 33.19674779261811
        },
        {
          "datetime": "2026-07-23 00:45:00",
          "close": 4148.6624,
          "rsi": 58.21632623780781,
          "rsi_ma": 66.20238753785635,
          "macd": 6.627526912472311,
          "macd_signal": 7.430291900950081,
          "alma": 4150.103764173089,
          "adx": 32.4931464722544
        },
        {
          "datetime": "2026-07-23 00:50:00",
          "close": 4148.29138,
          "rsi": 57.71706303746819,
          "rsi_ma": 65.46876645830072,
          "macd": 6.116482790174656,
          "macd_signal": 7.1675300787949965,
          "alma": 4149.613435257972,
          "adx": 31.609855812176605
        },
        {
          "datetime": "2026-07-23 00:55:00",
          "close": 4148.94485,
          "rsi": 58.393855096903216,
          "rsi_ma": 64.60294303598054,
          "macd": 5.69851724945513,
          "macd_signal": 6.873727512927023,
          "alma": 4149.11452797382,
          "adx": 30.416029413128637
        },
        {
          "datetime": "2026-07-23 01:00:00",
          "close": 4153.62062,
          "rsi": 62.96209301927653,
          "rsi_ma": 64.09133857816141,
          "macd": 5.679106899894759,
          "macd_signal": 6.63480339032057,
          "alma": 4149.9063063980075,
          "adx": 28.850883048966043
        },
        {
          "datetime": "2026-07-23 01:05:00",
          "close": 4154.91103,
          "rsi": 64.13253837546652,
          "rsi_ma": 63.53193661511988,
          "macd": 5.70211888357373,
          "macd_signal": 6.4482664889712025,
          "alma": 4151.587044208422,
          "adx": 28.35466888915103
        },
        {
          "datetime": "2026-07-23 01:10:00",
          "close": 4157.49399,
          "rsi": 66.42003069809205,
          "rsi_ma": 62.70408918623281,
          "macd": 5.861214894905418,
          "macd_signal": 6.330856170158046,
          "alma": 4153.8228188156345,
          "adx": 28.17415466966946
        },
        {
          "datetime": "2026-07-23 01:15:00",
          "close": 4154.45758,
          "rsi": 61.45794296515454,
          "rsi_ma": 62.08345631895763,
          "macd": 5.676847554553829,
          "macd_signal": 6.200054447037202,
          "alma": 4154.9871893156005,
          "adx": 28.369734446701926
        },
        {
          "datetime": "2026-07-23 01:20:00",
          "close": 4159.61376,
          "rsi": 66.09067191347665,
          "rsi_ma": 61.67895378096724,
          "macd": 5.879025990978609,
          "macd_signal": 6.135848755825483,
          "alma": 4156.33674427484,
          "adx": 28.43359551645504
        },
        {
          "datetime": "2026-07-23 01:25:00",
          "close": 4158.06666,
          "rsi": 63.61969556977435,
          "rsi_ma": 61.62571988705727,
          "macd": 5.847015068052398,
          "macd_signal": 6.078082018270866,
          "alma": 4157.256416597626,
          "adx": 28.921919550073113
        },
        {
          "datetime": "2026-07-23 01:30:00",
          "close": 4157.72316,
          "rsi": 63.05599581253536,
          "rsi_ma": 61.67470493079308,
          "macd": 5.727900925383118,
          "macd_signal": 6.008045799693317,
          "alma": 4157.78610829751,
          "adx": 29.566948309023665
        },
        {
          "datetime": "2026-07-23 01:35:00",
          "close": 4157.17923,
          "rsi": 62.11741730250601,
          "rsi_ma": 61.99304834797341,
          "macd": 5.525912227560939,
          "macd_signal": 5.911619085266841,
          "alma": 4157.790759718343,
          "adx": 29.85569849468078
        }
      ]
    }
  }
}